discordapi.py
discordapi-0.1.dist-info/WHEEL
discordapi-0.1.dist-info/METADATA
discordapi-0.1.dist-info/RECORD
